viirs_tools/__about__.py
viirs_tools/__init__.py
viirs_tools/__version__.py
viirs_tools/runner.py
viirs_tools/algs/__init__.py
viirs_tools/algs/cloud.py
viirs_tools/algs/index.py
viirs_tools/algs/lst.py
viirs_tools/algs/night.py
viirs_tools/algs/utils.py
viirs_tools/algs/water.py
viirs_tools/assimilator/__init__.py
viirs_tools/assimilator/assimilator.py
viirs_tools/assimilator/reading.py
viirs_tools/assimilator/reading_helpers.py
viirs_tools/utils/__init__.py
viirs_tools/utils/constants.py
viirs_tools/utils/types.py
viirs_tools-2.0.2.dist-info/METADATA
viirs_tools-2.0.2.dist-info/WHEEL
viirs_tools-2.0.2.dist-info/licenses/LICENSE
viirs_tools-2.0.2.dist-info/RECORD
