Metadata-Version: 2.4
Name: viirs-tools
Version: 2.0.2
Summary: Python library for processing VIIRS data
Project-URL: Documentation, https://github.com/Veon2479/viirs-tools#readme
Project-URL: Issues, https://github.com/Veon2479/viirs-tools/issues
Project-URL: Source, https://github.com/Veon2479/viirs-tools
Author-email: Andrey Shuliak <andriei.shuliak@gmail.com>
License: Apache-2.0
License-File: LICENSE
Keywords: meteorology,remote sensing,satellite,viirs
Classifier: Development Status :: 3 - Alpha
Classifier: Intended Audience :: Science/Research
Classifier: License :: OSI Approved :: Apache Software License
Classifier: Programming Language :: Python
Classifier: Programming Language :: Python :: 3.10
Classifier: Programming Language :: Python :: 3.11
Classifier: Programming Language :: Python :: 3.12
Classifier: Programming Language :: Python :: 3.13
Classifier: Topic :: Scientific/Engineering :: Atmospheric Science
Requires-Python: >=3.10
Requires-Dist: xarray
Provides-Extra: all
Requires-Dist: netcdf4; extra == 'all'
Provides-Extra: assimilator
Requires-Dist: netcdf4; extra == 'assimilator'
